RAM/dual_port_ram.v
module dual_port_ram 
      #(parameter d_width = 8,depth=8)
	(input clk,ena,enb,wea,web,
	input [d_width-1:0] din_a,din_b,
	input [$clog2(depth)-1:0] addr_a,addr_b,
	output  reg [d_width-1:0] dout_a,dout_b);
reg [d_width-1:0]mem[depth-1:0];
  always @(posedge clk)
  begin
      if (ena)
      begin
  	 if ( wea)
		mem[addr_a] <= din_a;
	  else 
		  dout_a <= mem[addr_a];
  end
       else
	       dout_a <= 0;
       end
 always @(posedge clk)
 begin
	 if (enb)
	 begin
		 if(web)
			  mem[addr_b] <= din_b;
          else
                  dout_b <= mem[addr_b];
  end
  else
	  dout_b <= 0;
  end
endmodule

RAM/tbdual_port_ram.v
module tbdual_port;
        parameter d_width = 8,depth=8;
        reg clk,ena,enb,wea,web;
        reg [d_width-1:0] din_a,din_b;
        reg [$clog2(depth)-1:0] addr_a,addr_b;
        wire [d_width-1:0] dout_a,dout_b;
dual_port_ram #(.d_width(d_width),.depth(depth)) uut (.*);
always #5 clk = ~clk;
task data_gen;
                integer i;
		begin
        for (i=0;i<depth;i++)#10
        begin
                addr_a <= i;
                addr_b <= i;
                din_a <= $random;
                din_b <= $random;
        end
end
endtask
initial begin
	clk =0;ena=0;enb=0;wea=0;web=0;addr_a=0;addr_b=0;din_a=0;din_b=0;
	#10;
	// case 1 
	$display("write operation in both port");
	ena = 1;enb=1;wea=1;web=1;#10;
	data_gen;#10;
//case 2
	$display("Port A write Port B read");
         ena = 1;enb=1;wea=1;web=0;#10;
	data_gen;#10;
//case 3	
	$display("Port A read Port B write");
	 ena = 1;enb=1;wea=0;web=1;#10;
	 data_gen;#10;
//case 4
	$display("Read operation in both");
	 ena = 1;enb=1;wea=0;web=0;#10;
	 data_gen;
	 #100 $finish;
 end
 initial begin 
	 $dumpfile("out_dport.vcd");
	 $dumpvars(0,tbdual_port);
	 $monitor("time=%0t  |ena=%b|enb=%b|wea=%b|web=%b|addr_a=%d|din_a=%d|dout_a=%d|addr_b=%d|din_b=%d|dout_b=%d",$time,ena,enb,
		 wea,web,addr_a,din_a,dout_a,addr_b,din_b,dout_b);
 end
 endmodule

RAM/out_dport.vcd
$date
	Sun Mar  8 06:49:56 2026
$end
$version
	Icarus Verilog
$end
$timescale
	1s
$end
$scope module tbdual_port $end
$var wire 8 ! dout_b [7:0] $end
$var wire 8 " dout_a [7:0] $end
$var parameter 32 # d_width $end
$var parameter 32 $ depth $end
$var reg 3 % addr_a [2:0] $end
$var reg 3 & addr_b [2:0] $end
$var reg 1 ' clk $end
$var reg 8 ( din_a [7:0] $end
$var reg 8 ) din_b [7:0] $end
$var reg 1 * ena $end
$var reg 1 + enb $end
$var reg 1 , wea $end
$var reg 1 - web $end
$scope module uut $end
$var wire 3 . addr_a [2:0] $end
$var wire 3 / addr_b [2:0] $end
$var wire 1 ' clk $end
$var wire 8 0 din_a [7:0] $end
$var wire 8 1 din_b [7:0] $end
$var wire 1 * ena $end
$var wire 1 + enb $end
$var wire 1 , wea $end
$var wire 1 - web $end
$var parameter 32 2 d_width $end
$var parameter 32 3 depth $end
$var reg 8 4 dout_a [7:0] $end
$var reg 8 5 dout_b [7:0] $end
$upscope $end
$scope task data_gen $end
$var integer 32 6 i [31:0] $end
$upscope $end
$upscope $end
$enddefinitions $end
$comment Show the parameter values. $end
$dumpall
b1000 3
b1000 2
b1000 $
b1000 #
$end
#0
$dumpvars
bx 6
bx 5
bx 4
b0 1
b0 0
b0 /
b0 .
0-
0,
0+
0*
b0 )
b0 (
0'
b0 &
b0 %
bx "
bx !
$end
#5
b0 "
b0 4
b0 !
b0 5
1'
#10
0'
1-
1,
1+
1*
#15
1'
#20
0'
b0 6
#25
1'
#30
b10000001 )
b10000001 1
b100100 (
b100100 0
0'
b1 6
#35
1'
#40
b1100011 )
b1100011 1
b1001 (
b1001 0
b1 &
b1 /
b1 %
b1 .
0'
b10 6
#45
1'
#50
b10001101 )
b10001101 1
b1101 (
b1101 0
b10 &
b10 /
b10 %
b10 .
0'
b11 6
#55
1'
#60
b10010 )
b10010 1
b1100101 (
b1100101 0
b11 &
b11 /
b11 %
b11 .
0'
b100 6
#65
1'
#70
b1101 )
b1101 1
b1 (
b1 0
b100 &
b100 /
b100 %
b100 .
0'
b101 6
#75
1'
#80
b111101 )
b111101 1
b1110110 (
b1110110 0
b101 &
b101 /
b101 %
b101 .
0'
b110 6
#85
1'
#90
b10001100 )
b10001100 1
b11101101 (
b11101101 0
b110 &
b110 /
b110 %
b110 .
0'
b111 6
#95
1'
#100
b11000110 )
b11000110 1
b11111001 (
b11111001 0
b111 &
b111 /
b111 %
b111 .
0'
b1000 6
#105
1'
#110
0'
0-
#115
b11111001 !
b11111001 5
1'
#120
0'
b0 6
#125
1'
#130
b10101010 )
b10101010 1
b11000101 (
b11000101 0
b0 &
b0 /
b0 %
b0 .
0'
b1 6
#135
b10000001 !
b10000001 5
1'
#140
b1110111 )
b1110111 1
b11100101 (
b11100101 0
b1 &
b1 /
b1 %
b1 .
0'
b10 6
#145
b1001 !
b1001 5
1'
#150
b10001111 )
b10001111 1
b10010 (
b10010 0
b10 &
b10 /
b10 %
b10 .
0'
b11 6
#155
b10001101 !
b10001101 5
1'
#160
b11001110 )
b11001110 1
b11110010 (
b11110010 0
b11 &
b11 /
b11 %
b11 .
0'
b100 6
#165
b1100101 !
b1100101 5
1'
#170
b11000101 )
b11000101 1
b11101000 (
b11101000 0
b100 &
b100 /
b100 %
b100 .
0'
b101 6
#175
b1101 !
b1101 5
1'
#180
b10111101 )
b10111101 1
b1011100 (
b1011100 0
b101 &
b101 /
b101 %
b101 .
0'
b110 6
#185
b1110110 !
b1110110 5
1'
#190
b1100101 )
b1100101 1
b101101 (
b101101 0
b110 &
b110 /
b110 %
b110 .
0'
b111 6
#195
b10001100 !
b10001100 5
1'
#200
b1010 )
b1010 1
b1100011 (
b1100011 0
b111 &
b111 /
b111 %
b111 .
0'
b1000 6
#205
b11111001 !
b11111001 5
1'
#210
0'
1-
0,
#215
b1100011 "
b1100011 4
1'
#220
0'
b0 6
#225
b1010 "
b1010 4
1'
#230
b100000 )
b100000 1
b10000000 (
b10000000 0
b0 &
b0 /
b0 %
b0 .
0'
b1 6
#235
b11000101 "
b11000101 4
1'
#240
b10011101 )
b10011101 1
b10101010 (
b10101010 0
b1 &
b1 /
b1 %
b1 .
0'
b10 6
#245
b11100101 "
b11100101 4
1'
#250
b10011 )
b10011 1
b10010110 (
b10010110 0
b10 &
b10 /
b10 %
b10 .
0'
b11 6
#255
b10010 "
b10010 4
1'
#260
b1010011 )
b1010011 1
b1101 (
b1101 0
b11 &
b11 /
b11 %
b11 .
0'
b100 6
#265
b11110010 "
b11110010 4
1'
#270
b11010101 )
b11010101 1
b1101011 (
b1101011 0
b100 &
b100 /
b100 %
b100 .
0'
b101 6
#275
b11101000 "
b11101000 4
1'
#280
b10101110 )
b10101110 1
b10 (
b10 0
b101 &
b101 /
b101 %
b101 .
0'
b110 6
#285
b1011100 "
b1011100 4
1'
#290
b11001111 )
b11001111 1
b11101 (
b11101 0
b110 &
b110 /
b110 %
b110 .
0'
b111 6
#295
b101101 "
b101101 4
1'
#300
b1010 )
b1010 1
b100011 (
b100011 0
b111 &
b111 /
b111 %
b111 .
0'
b1000 6
#305
b1010 "
b1010 4
1'
#310
0'
0-
#315
b1010 !
b1010 5
1'
#320
0'
b0 6
#325
1'
#330
b111100 )
b111100 1
b11001010 (
b11001010 0
b0 &
b0 /
b0 %
b0 .
0'
b1 6
#335
b100000 !
b100000 5
b100000 "
b100000 4
1'
#340
b10001010 )
b10001010 1
b11110010 (
b11110010 0
b1 &
b1 /
b1 %
b1 .
0'
b10 6
#345
b10011101 "
b10011101 4
b10011101 !
b10011101 5
1'
#350
b11011000 )
b11011000 1
b1000001 (
b1000001 0
b10 &
b10 /
b10 %
b10 .
0'
b11 6
#355
b10011 !
b10011 5
b10011 "
b10011 4
1'
#360
b10001001 )
b10001001 1
b1111000 (
b1111000 0
b11 &
b11 /
b11 %
b11 .
0'
b100 6
#365
b1010011 "
b1010011 4
b1010011 !
b1010011 5
1'
#370
b10110110 )
b10110110 1
b11101011 (
b11101011 0
b100 &
b100 /
b100 %
b100 .
0'
b101 6
#375
b11010101 !
b11010101 5
b11010101 "
b11010101 4
1'
#380
b10101110 )
b10101110 1
b11000110 (
b11000110 0
b101 &
b101 /
b101 %
b101 .
0'
b110 6
#385
b10101110 "
b10101110 4
b10101110 !
b10101110 5
1'
#390
b101010 )
b101010 1
b10111100 (
b10111100 0
b110 &
b110 /
b110 %
b110 .
0'
b111 6
#395
b11001111 !
b11001111 5
b11001111 "
b11001111 4
1'
#400
b1110001 )
b1110001 1
b1011 (
b1011 0
b111 &
b111 /
b111 %
b111 .
0'
b1000 6
#405
b1010 "
b1010 4
b1010 !
b1010 5
1'
