RAM/single_port_ram.v
module single_port_ram
	#(parameter d_width=8,depth=8)
	(input en,we, clk,
	input [$clog2(depth)-1:0]addr,	
	input [d_width-1:0]din,
	output reg [d_width-1:0]dout);
reg [d_width-1:0]mem_ram[depth-1:0];
always @ (posedge clk)
begin 
       if(en && we) begin      // write
		mem_ram[addr]<=din;
		dout <= 0;
	end
	else if (en && !we)  //read
		dout <= mem_ram[addr];
	else 
		dout <= 0; 
/*	       if (en)
	       begin
		       if(we)
			       mem_ram[addr] = din;
		       else
			       dout = mem_ram[addr];
	       end
	       else
		       dout = 0; */
end
endmodule

RAM/tbsingle_port_ram.v
module tbsingle_port_ram;
	parameter d_width=8,depth=8;
	reg en,we;
	reg clk;
	reg [$clog2(depth)-1:0]addr;
	reg [d_width-1:0]din;
	wire [d_width-1:0]dout;
	integer i;
single_port_ram #(.d_width(d_width),.depth(depth)) uut (.*);
//single_port_ram #(.d_width(d_width),.depth(depth)) uut (.clk(clk),.en(en),.we(we),.addr(addr),.din(din),.dout(dout));
always #5 clk = ~clk;
initial begin
        clk=0;
	en=0;we=1;din=$random;addr=4'b0000;
	#10;en=1;we=1;#10;
	for ( i=0;i<depth;i++)#10
	begin
		addr <= i;
		din <= $random;
	end
	#10;we=0;repeat (5) #10 addr = $random;
//	addr = 3'b011;#10;addr=3'b001;
	#100 $finish;
end
initial begin
	$dumpfile("out_sport.vcd");
	$dumpvars(0,tbsingle_port_ram);
	$monitor("time=%0t | en=%b | we=%b | addr=%4b | din=%d | dout=%d ",$time,en,we,addr,din,dout);
end
endmodule

RAM/out_sport.vcd
$date
	Mon Mar  9 07:34:00 2026
$end
$version
	Icarus Verilog
$end
$timescale
	1s
$end
$scope module tbsingle_port_ram $end
$var wire 8 ! dout [7:0] $end
$var parameter 32 " d_width $end
$var parameter 32 # depth $end
$var reg 3 $ addr [2:0] $end
$var reg 1 % clk $end
$var reg 8 & din [7:0] $end
$var reg 1 ' en $end
$var reg 1 ( we $end
$var integer 32 ) i [31:0] $end
$scope module uut $end
$var wire 3 * addr [2:0] $end
$var wire 1 % clk $end
$var wire 8 + din [7:0] $end
$var wire 1 ' en $end
$var wire 1 ( we $end
$var parameter 32 , d_width $end
$var parameter 32 - depth $end
$var reg 8 . dout [7:0] $end
$upscope $end
$upscope $end
$enddefinitions $end
$comment Show the parameter values. $end
$dumpall
b1000 -
b1000 ,
b1000 #
b1000 "
$end
#0
$dumpvars
bx .
b100100 +
b0 *
bx )
1(
0'
b100100 &
0%
b0 $
bx !
$end
#5
b0 !
b0 .
1%
#10
0%
1'
#15
1%
#20
0%
b0 )
#25
1%
#30
b10000001 &
b10000001 +
0%
b1 )
#35
1%
#40
b1001 &
b1001 +
b1 $
b1 *
0%
b10 )
#45
1%
#50
b1100011 &
b1100011 +
b10 $
b10 *
0%
b11 )
#55
1%
#60
b1101 &
b1101 +
b11 $
b11 *
0%
b100 )
#65
1%
#70
b10001101 &
b10001101 +
b100 $
b100 *
0%
b101 )
#75
1%
#80
b1100101 &
b1100101 +
b101 $
b101 *
0%
b110 )
#85
1%
#90
b10010 &
b10010 +
b110 $
b110 *
0%
b111 )
#95
1%
#100
b1 &
b1 +
b111 $
b111 *
0%
b1000 )
#105
1%
#110
0%
0(
#115
b1 !
b1 .
1%
#120
0%
b101 $
b101 *
#125
b1100101 !
b1100101 .
1%
#130
0%
b110 $
b110 *
#135
b10010 !
b10010 .
1%
#140
0%
b101 $
b101 *
#145
b1100101 !
b1100101 .
1%
#150
0%
#155
1%
#160
0%
b100 $
b100 *
#165
b10001101 !
b10001101 .
1%
