RAM/dual_port_ram.v
module dual_port_ram 
      #(parameter d_width = 8,depth=8)
	(input clk,ena,enb,wea,web,
	input [d_width-1:0] din_a,din_b,
	input [$clog2(depth)-1:0] addr_a,addr_b,
	output  reg [d_width-1:0] dout_a,dout_b);
reg [d_width-1:0]mem[depth-1:0];
  always @(posedge clk)
  begin
      if (ena)
      begin
  	 if ( wea)
		mem[addr_a] <= din_a;
	  else 
		  dout_a <= mem[addr_a];
  end
       else
	       dout_a <= 0;
       end
 always @(posedge clk)
 begin
	 if (enb)
	 begin
		 if(web)
			  mem[addr_b] <= din_b;
          else
                  dout_b <= mem[addr_b];
  end
  else
	  dout_b <= 0;
  end
endmodule

RAM/tbdual_port_ram.v
module tbdual_port;
        parameter d_width = 8,depth=8;
        reg clk,ena,enb,wea,web;
        reg [d_width-1:0] din_a,din_b;
        reg [$clog2(depth)-1:0] addr_a,addr_b;
        wire [d_width-1:0] dout_a,dout_b;
dual_port_ram #(.d_width(d_width),.depth(depth)) uut (.*);
always #5 clk = ~clk;
task data_gen;
                integer i;
		begin
        for (i=0;i<depth;i++)#10
        begin
                addr_a <= i;
                addr_b <= i;
                din_a <= $random;
                din_b <= $random;
        end
end
endtask
initial begin
	clk =0;ena=0;enb=0;wea=0;web=0;addr_a=0;addr_b=0;din_a=0;din_b=0;
	#10;
	// case 1 
	$display("write operation in both port");
	ena = 1;enb=1;wea=1;web=1;#10;
//case 2
	$display("Port A write Port B read");
         ena = 1;enb=1;wea=1;web=0;#10;
	data_gen;
//case 3	
	$display("Port A read Port B write");
	 ena = 1;enb=1;wea=0;web=1;#10;
	 data_gen;
//case 4
	$display("Read operation in both");
	 ena = 1;enb=1;wea=0;web=0;#10;
	 data_gen;
	 #100 $finish;
 end
 initial begin 
	 $dumpfile("out_dport.vcd");
	 $dumpvars(0,tbdual_port);
	 $monitor("time=%0t  |ena=%b|enb=%b|wea=%b|web=%b|addr_a=%d|din_a=%d|dout_a=%d|addr_b=%d|din_b=%d|dout_b=%d",$time,ena,enb,
		 wea,web,addr_a,din_a,dout_a,addr_b,din_b,dout_b);
 end
 endmodule

RAM/out_dport.vcd
$date
	Fri Mar  6 13:33:10 2026
$end
$version
	Icarus Verilog
$end
$timescale
	1s
$end
$scope module tbdual_port $end
$var wire 8 ! dout_b [7:0] $end
$var wire 8 " dout_a [7:0] $end
$var parameter 32 # d_width $end
$var parameter 32 $ depth $end
$var reg 3 % addr_a [2:0] $end
$var reg 3 & addr_b [2:0] $end
$var reg 1 ' clk $end
$var reg 8 ( din_a [7:0] $end
$var reg 8 ) din_b [7:0] $end
$var reg 1 * ena $end
$var reg 1 + enb $end
$var reg 1 , wea $end
$var reg 1 - web $end
$scope module uut $end
$var wire 3 . addr_a [2:0] $end
$var wire 3 / addr_b [2:0] $end
$var wire 1 ' clk $end
$var wire 8 0 din_a [7:0] $end
$var wire 8 1 din_b [7:0] $end
$var wire 1 * ena $end
$var wire 1 + enb $end
$var wire 1 , wea $end
$var wire 1 - web $end
$var parameter 32 2 d_width $end
$var parameter 32 3 depth $end
$var reg 8 4 dout_a [7:0] $end
$var reg 8 5 dout_b [7:0] $end
$upscope $end
$scope task data_gen $end
$var integer 32 6 i [31:0] $end
$upscope $end
$upscope $end
$enddefinitions $end
$comment Show the parameter values. $end
$dumpall
b1000 3
b1000 2
b1000 $
b1000 #
$end
#0
$dumpvars
bx 6
bx 5
bx 4
b0 1
b0 0
b0 /
b0 .
0-
0,
0+
0*
b0 )
b0 (
0'
b0 &
b0 %
bx "
bx !
$end
#5
b0 "
b0 4
b0 !
b0 5
1'
#10
0'
1-
1,
1+
1*
#15
1'
#20
0'
0-
#25
1'
#30
0'
b0 6
#35
1'
#40
b10000001 )
b10000001 1
b100100 (
b100100 0
0'
b1 6
#45
1'
#50
b1100011 )
b1100011 1
b1001 (
b1001 0
b1 &
b1 /
b1 %
b1 .
0'
b10 6
#55
bx !
bx 5
1'
#60
b10001101 )
b10001101 1
b1101 (
b1101 0
b10 &
b10 /
b10 %
b10 .
0'
b11 6
#65
1'
#70
b10010 )
b10010 1
b1100101 (
b1100101 0
b11 &
b11 /
b11 %
b11 .
0'
b100 6
#75
1'
#80
b1101 )
b1101 1
b1 (
b1 0
b100 &
b100 /
b100 %
b100 .
0'
b101 6
#85
1'
#90
b111101 )
b111101 1
b1110110 (
b1110110 0
b101 &
b101 /
b101 %
b101 .
0'
b110 6
#95
1'
#100
b10001100 )
b10001100 1
b11101101 (
b11101101 0
b110 &
b110 /
b110 %
b110 .
0'
b111 6
#105
1'
#110
b11000110 )
b11000110 1
b11111001 (
b11111001 0
b111 &
b111 /
b111 %
b111 .
0'
1-
0,
b1000 6
#115
bx "
bx 4
1'
#120
0'
b0 6
#125
b11000110 "
b11000110 4
1'
#130
b10101010 )
b10101010 1
b11000101 (
b11000101 0
b0 &
b0 /
b0 %
b0 .
0'
b1 6
#135
b100100 "
b100100 4
1'
#140
b1110111 )
b1110111 1
b11100101 (
b11100101 0
b1 &
b1 /
b1 %
b1 .
0'
b10 6
#145
b1001 "
b1001 4
1'
#150
b10001111 )
b10001111 1
b10010 (
b10010 0
b10 &
b10 /
b10 %
b10 .
0'
b11 6
#155
b1101 "
b1101 4
1'
#160
b11001110 )
b11001110 1
b11110010 (
b11110010 0
b11 &
b11 /
b11 %
b11 .
0'
b100 6
#165
b1100101 "
b1100101 4
1'
#170
b11000101 )
b11000101 1
b11101000 (
b11101000 0
b100 &
b100 /
b100 %
b100 .
0'
b101 6
#175
b1 "
b1 4
1'
#180
b10111101 )
b10111101 1
b1011100 (
b1011100 0
b101 &
b101 /
b101 %
b101 .
0'
b110 6
#185
b1110110 "
b1110110 4
1'
#190
b1100101 )
b1100101 1
b101101 (
b101101 0
b110 &
b110 /
b110 %
b110 .
0'
b111 6
#195
b11101101 "
b11101101 4
1'
#200
b1010 )
b1010 1
b1100011 (
b1100011 0
b111 &
b111 /
b111 %
b111 .
0'
0-
b1000 6
#205
b11000110 "
b11000110 4
b11000110 !
b11000110 5
1'
#210
0'
b0 6
#215
1'
#220
b100000 )
b100000 1
b10000000 (
b10000000 0
b0 &
b0 /
b0 %
b0 .
0'
b1 6
#225
b10101010 "
b10101010 4
b10101010 !
b10101010 5
1'
#230
b10011101 )
b10011101 1
b10101010 (
b10101010 0
b1 &
b1 /
b1 %
b1 .
0'
b10 6
#235
b1110111 !
b1110111 5
b1110111 "
b1110111 4
1'
#240
b10011 )
b10011 1
b10010110 (
b10010110 0
b10 &
b10 /
b10 %
b10 .
0'
b11 6
#245
b10001111 "
b10001111 4
b10001111 !
b10001111 5
1'
#250
b1010011 )
b1010011 1
b1101 (
b1101 0
b11 &
b11 /
b11 %
b11 .
0'
b100 6
#255
b11001110 !
b11001110 5
b11001110 "
b11001110 4
1'
#260
b11010101 )
b11010101 1
b1101011 (
b1101011 0
b100 &
b100 /
b100 %
b100 .
0'
b101 6
#265
b11000101 "
b11000101 4
b11000101 !
b11000101 5
1'
#270
b10101110 )
b10101110 1
b10 (
b10 0
b101 &
b101 /
b101 %
b101 .
0'
b110 6
#275
b10111101 !
b10111101 5
b10111101 "
b10111101 4
1'
#280
b11001111 )
b11001111 1
b11101 (
b11101 0
b110 &
b110 /
b110 %
b110 .
0'
b111 6
#285
b1100101 "
b1100101 4
b1100101 !
b1100101 5
1'
#290
b1010 )
b1010 1
b100011 (
b100011 0
b111 &
b111 /
b111 %
b111 .
0'
b1000 6
#295
b11000110 !
b11000110 5
b11000110 "
b11000110 4
1'
