sync_FIFO.v
module sync_fifo
      # ( parameter d_width= 16 ,depth = 9)
	(input w,r,clk,rst,             // w - write , r - read
	input [d_width-1:0] din,
  	output full,empty,	
	output reg [d_width-1:0] dout,
output reg [3:0] wptr,rptr);                          // wptr - write pointer, rptr - read pointer
reg [d_width-1:0] fifo_mem [depth-1:0];
integer i;

always @(posedge clk)       // write operation
begin
	if(rst)
	begin
		for ( i=0;i<depth;i++)
		begin
		fifo_mem[i] <= 0;
		wptr <= 0;
	end
	end
	else if ( w && !full)
	begin
		fifo_mem[wptr[3:0]] <= din;
		if (wptr == 4'b1001)
			wptr <= 0;
		else
	        wptr <= wptr + 1;
	end
end
always @(posedge clk)     // read operation
begin
	if(rst)
	begin
		dout <= 0;
		rptr <= 0;
	end
	else if ( r && !empty)
	begin
		dout <= fifo_mem[rptr[3:0]];
		if (rptr == 4'b1001)
			rptr <= 0;
		else
		rptr <= rptr + 1;
	end
end
//assign full = ((wptr[3] != rptr[3]) && (wptr[2:0] == rptr[2:0]));
//assign full = (wptr == 4'b1000 && rptr == 4'b0000);
assign full = (wptr + 1'b1) == rptr;
assign empty = (wptr[3:0] == rptr[3:0]) ;
endmodule

tbsync_FIFO.v
module tbsync_fifo;
	reg w,r,clk,rst;
	wire empty,full;
        reg [15:0] din;
	wire[15:0] dout;
	wire[3:0] wptr,rptr;
sync_fifo uut(.w(w),.r(r),.clk(clk),.rst(rst),.empty(empty),.full(full),.din(din),.dout(dout),.wptr(wptr),.rptr(rptr));

always #5 clk = ~clk;
initial begin
	clk=0;rst=1;w=0;r=0;din=$random;
	#10;
	rst=0;#10;
	w=1;#10;din= $random;#10;
	r=1;#10;
	w=0;din=$random;#10;
	w=1;#10;r=0;#40;din=$random;
	#10;r=1;
	#100 $finish;
end
initial begin 
	$dumpfile("out_fifo.vcd");
	$dumpvars(0,tbsync_fifo);
	$monitor("time=%0t,rst=%b,w=%b,wptr=%d,r=%b,rptr=%d,full=%b,empty=%b,din=%d,dout=%d",$time,rst,w,wptr,r,rptr,full,empty,din,dout);
end
endmodule

out_fifo.vcd
$date
	Thu Mar  5 13:03:17 2026
$end
$version
	Icarus Verilog
$end
$timescale
	1s
$end
$scope module tbsync_fifo $end
$var wire 4 ! wptr [3:0] $end
$var wire 4 " rptr [3:0] $end
$var wire 1 # full $end
$var wire 1 $ empty $end
$var wire 16 % dout [15:0] $end
$var reg 1 & clk $end
$var reg 16 ' din [15:0] $end
$var reg 1 ( r $end
$var reg 1 ) rst $end
$var reg 1 * w $end
$scope module uut $end
$var wire 1 & clk $end
$var wire 16 + din [15:0] $end
$var wire 1 ( r $end
$var wire 1 ) rst $end
$var wire 1 * w $end
$var wire 1 # full $end
$var wire 1 $ empty $end
$var parameter 32 , d_width $end
$var parameter 32 - depth $end
$var reg 16 . dout [15:0] $end
$var reg 4 / rptr [3:0] $end
$var reg 4 0 wptr [3:0] $end
$var integer 32 1 i [31:0] $end
$upscope $end
$upscope $end
$enddefinitions $end
$comment Show the parameter values. $end
$dumpall
b1001 -
b10000 ,
$end
#0
$dumpvars
bx 1
bx 0
bx /
bx .
b11010100100100 +
0*
1)
0(
b11010100100100 '
0&
bx %
x$
x#
bx "
bx !
$end
#5
0#
1$
b0 !
b0 0
b0 "
b0 /
b0 %
b0 .
b1001 1
1&
#10
0&
0)
#15
1&
#20
0&
1*
#25
0$
b1 !
b1 0
1&
#30
0&
b101111010000001 '
b101111010000001 +
#35
b10 !
b10 0
1&
#40
0&
1(
#45
b11 !
b11 0
b1 "
b1 /
b11010100100100 %
b11010100100100 .
1&
#50
0&
b1101011000001001 '
b1101011000001001 +
0*
#55
b10 "
b10 /
b101111010000001 %
b101111010000001 .
1&
#60
0&
1*
#65
b100 !
b100 0
0$
b11 "
b11 /
1&
#70
0&
0(
#75
b101 !
b101 0
1&
#80
0&
#85
b110 !
b110 0
1&
#90
0&
#95
b111 !
b111 0
1&
#100
0&
#105
b1000 !
b1000 0
1&
#110
0&
b101011001100011 '
b101011001100011 +
#115
b1001 !
b1001 0
1&
#120
0&
1(
#125
b0 !
b0 0
b100 "
b100 /
b1101011000001001 %
b1101011000001001 .
1&
#130
0&
#135
b101 "
b101 /
b1 !
b1 0
1&
#140
0&
#145
b10 !
b10 0
b110 "
b110 /
1&
#150
0&
#155
b111 "
b111 /
b11 !
b11 0
1&
#160
0&
#165
b100 !
b100 0
b1000 "
b1000 /
1&
#170
0&
#175
b1001 "
b1001 /
b101011001100011 %
b101011001100011 .
b101 !
b101 0
1&
#180
0&
#185
b110 !
b110 0
b0 "
b0 /
bx %
bx .
1&
#190
0&
#195
b1 "
b1 /
b101011001100011 %
b101011001100011 .
b111 !
b111 0
1&
#200
0&
#205
b1000 !
b1000 0
b10 "
b10 /
1&
#210
0&
#215
b11 "
b11 /
b1001 !
b1001 0
1&
