seq.v
module mealy_1011(input clk,rst,x,output reg y);
  reg [1:0]s,ns;
  parameter s0=2'b00,
  			s1=2'b01,
  			s2=2'b10,
  			s3=2'b11;
  always @(posedge clk or posedge rst) begin
    if(rst)
      s<=s0;
    else
      s<=ns;
  end
  always @(*)begin

    case(s)
      s0:begin
        if(x)
          ns=s1;
        else
          ns=s0;
      end
      s1:begin
        if(x)
          ns=s1;
        else
          ns=s2;
      end
      s2:begin
        if(x)
          ns=s3;
        else
          ns=s0;
      end
      s3:begin
	      if(x) 
          ns=s1;
        else
          ns=s2;
      end
      default: ns=s0;
    endcase
  end
  always @(posedge clk or posedge rst)
begin
   if(rst)
      y = 0;
   else
      y = (s==s3 && x);
end
endmodule

tb_seq.v
module mealy_1011_tb;
  reg clk,rst,x;
  wire y;
  mealy_1011 dut(.*);
  initial begin
    $dumpfile("out_mealy_1011.vcd");
    $dumpvars(0,mealy_1011_tb);
    $monitor("time=%0t | rst=%b | clk=%b | x=%b | y=%b",$time,rst,clk,x,y);
  end
  always #5 clk=~clk;
  initial begin
    clk=1;
    rst=1;#10;
    rst=0;
    x=1; #10;
    x=1; #10;
    x=0; #10;
    x=1; #10;
    x=0; #10;
    x=1; #10;
    x=1; #10;   
    x=0; #10;
    x=1; #10;
    x=1; #10;   
	$finish;
  end
endmodule

out_mealy_1011.vcd
$date
	Tue Feb 17 04:24:53 2026
$end
$version
	Icarus Verilog
$end
$timescale
	1s
$end
$scope module mealy_1011_tb $end
$var wire 1 ! y $end
$var reg 1 " clk $end
$var reg 1 # rst $end
$var reg 1 $ x $end
$scope module dut $end
$var wire 1 " clk $end
$var wire 1 # rst $end
$var wire 1 $ x $end
$var parameter 2 % s0 $end
$var parameter 2 & s1 $end
$var parameter 2 ' s2 $end
$var parameter 2 ( s3 $end
$var reg 2 ) ns [1:0] $end
$var reg 2 * s [1:0] $end
$var reg 1 ! y $end
$upscope $end
$upscope $end
$enddefinitions $end
$comment Show the parameter values. $end
$dumpall
b11 (
b10 '
b1 &
b0 %
$end
#0
$dumpvars
b0 *
b0 )
x$
1#
1"
0!
$end
#5
0"
#10
b1 *
b1 )
1"
1$
0#
#15
0"
#20
1"
#25
0"
#30
b10 *
b0 )
1"
0$
#35
0"
#40
b11 *
b1 )
1"
1$
#45
0"
#50
b10 *
b0 )
1"
0$
#55
0"
#60
b11 *
b1 )
1"
1$
#65
0"
#70
b1 *
1!
1"
#75
0"
#80
b10 *
0!
b0 )
1"
0$
#85
0"
#90
b11 *
b1 )
1"
1$
#95
0"
#100
b1 *
1!
1"
#105
0"
#110
0!
1"
