sequential/ff_converstion/t_jk_con.v
module t_ff(
	input t,clk,rst,
	output reg q);
always@(posedge clk or negedge rst)
begin
	if (rst)
	 q<=0;
	else if(t)
		q<=~q;
	else 
		q<=q;
end
endmodule
module c_jk(
	input j,k,clk,rst,
	output q);
wire q1;
assign q1 = j&q|k&~q;
    t_ff t1 (.t(q1),.clk(clk),.rst(rst),.q(q));
    endmodule

sequential/ff_converstion/tb_jkcon.v
module tb_jkcon;
        reg j,k,clk,rst;
        wire q;

c_jk uut(.j(j),.k(k),.clk(clk),.rst(rst),.q(q));

        always #5 clk=~clk;
        initial begin
                clk = 1;
		rst =0;
                j=0;k=1;#10;rst=1;#5
                j=1;k=0;#10;
                j=0;k=0;#10;rst=0;#5
                j=1;k=1;
                #100 $finish;
        end
        initial begin
        $dumpfile("out_jkcon.vcd");
        $dumpvars(0,tb_jkcon);
        $monitor("time=%0t,j=%b,k=%b,clk=%b,rst=%b,q=%b",$time,j,k,clk,rst,q);
        end
        endmodule

sequential/ff_converstion/out_jkcon.vcd
$date
	Tue Feb 17 05:45:38 2026
$end
$version
	Icarus Verilog
$end
$timescale
	1s
$end
$scope module tb_jkcon $end
$var wire 1 ! q $end
$var reg 1 " clk $end
$var reg 1 # j $end
$var reg 1 $ k $end
$var reg 1 % rst $end
$scope module uut $end
$var wire 1 " clk $end
$var wire 1 # j $end
$var wire 1 $ k $end
$var wire 1 & q1 $end
$var wire 1 % rst $end
$var wire 1 ! q $end
$scope module t1 $end
$var wire 1 " clk $end
$var wire 1 % rst $end
$var wire 1 & t $end
$var reg 1 ! q $end
$upscope $end
$upscope $end
$upscope $end
$enddefinitions $end
$comment Show the parameter values. $end
$dumpall
$end
#0
$dumpvars
x&
0%
1$
0#
1"
x!
$end
#5
0"
#10
1&
0!
1"
1%
#15
0&
0"
0$
1#
#20
1"
#25
0"
0#
#30
1"
#35
0"
0%
#40
1&
1"
1$
1#
#45
0"
#50
1!
1"
#55
0"
#60
1&
0!
1"
#65
0"
#70
1!
1"
#75
0"
#80
1&
0!
1"
#85
0"
#90
1!
1"
#95
0"
#100
1&
0!
1"
#105
0"
#110
1!
1"
#115
0"
#120
1&
0!
1"
#125
0"
#130
1!
1"
#135
0"
#140
1&
0!
1"
