sequential/ff_converstion/sr_con.v
 module sr_ff(
        input s,r,clk,
        output reg  q);

always@(posedge clk)
begin
case ({s,r})
         2'b00: q <= q;
         2'b01: q <= 0;
         2'b10: q <= 1;
         2'b11: q <= 1'bx;
         default: q <=1'b0 ;
endcase
end
endmodule

module sr_c_jk(
	input j,k,clk,
	output q);
	wire q1,q2;
	assign q1 = j & ~q;
	assign q2 = k & q;
 	sr_ff sr1 (.s(q1),.r(q2),.clk(clk),.q(q));
	endmodule

sequential/ff_converstion/tb_srcon.v
module tb_srcon;
        reg j,k,clk;
        wire q;

sr_c_jk uut(.j(j),.k(k),.clk(clk),.q(q));

        always #5 clk=~clk;
        initial begin
                clk = 1;
                j=0;k=1;#10;
                j=1;k=0;#10;
                j=0;k=0;#10;
                j=1;k=1;
                #60 $finish;
        end
        initial begin
        $dumpfile("out_srcon.vcd");
        $dumpvars(0,tb_srcon);
        $monitor("time=%0t,j=%b,k=%b,clk=%b,q=%b",$time,j,k,clk,q);
        end
        endmodule

sequential/ff_converstion/out_srcon.vcd
$date
	Tue Feb 17 06:22:12 2026
$end
$version
	Icarus Verilog
$end
$timescale
	1s
$end
$scope module tb_srcon $end
$var wire 1 ! q $end
$var reg 1 " clk $end
$var reg 1 # j $end
$var reg 1 $ k $end
$scope module uut $end
$var wire 1 " clk $end
$var wire 1 # j $end
$var wire 1 $ k $end
$var wire 1 % q1 $end
$var wire 1 & q2 $end
$var wire 1 ! q $end
$scope module sr1 $end
$var wire 1 " clk $end
$var wire 1 & r $end
$var wire 1 % s $end
$var reg 1 ! q $end
$upscope $end
$upscope $end
$upscope $end
$enddefinitions $end
$comment Show the parameter values. $end
$dumpall
$end
#0
$dumpvars
0&
0%
1$
0#
1"
0!
$end
#5
0"
#10
1!
0%
1"
0$
1#
#15
0"
#20
1"
0#
#25
0"
#30
1%
0!
0&
1"
1$
1#
#35
0"
#40
0%
1&
1!
1"
#45
0"
#50
1%
0&
0!
1"
#55
0"
#60
0%
1&
1!
1"
#65
0"
#70
1%
0&
0!
1"
#75
0"
#80
0%
1&
1!
1"
#85
0"
#90
1%
0&
0!
1"
