FIFO/sync_FIFO.v
module sync_fifo
      # ( parameter d_width= 16 ,depth = 8)
	(input w,r,clk,rst,             // w - write , r - read
	input [d_width-1:0] din,
  	output full,empty,	
	output reg [d_width-1:0] dout,
output reg [$clog2(depth)-1:0] wptr,rptr);                          // wptr - write pointer, rptr - read pointe$r
reg [d_width-1:0] fifo_mem [depth-1:0];
integer i;

always @(posedge clk)       // write operation
begin
	if(rst)
	begin
		for ( i=0;i<depth;i++)
		begin
		fifo_mem[i] <= 0;
		wptr <= 0;
	end
	end
	else if ( w && !full)
	begin
		if (wptr == depth )
			wptr <= 0;
		else begin
		fifo_mem[wptr[3:0]] <= din;
		wptr <= wptr + 1'b1;
	end
end
end
always @(posedge clk)     // read operation
begin
	if(rst)
	begin
		dout <= 0;
		rptr <= 0;
	end
	else if ( r && !empty)
	begin
		if (rptr == depth)
			rptr <= 0;
		else begin
		dout <= fifo_mem[rptr[3:0]];
		rptr <= rptr + 1'b1;
	end
end
end
//assign full = ((wptr[3] != rptr[3]) && (wptr[2:0] == rptr[2:0]));
//assign full = (wptr == 4'b1000 && rptr == 4'b0000);
assign full = (wptr + 1'b1) == rptr;
assign empty = (wptr[3:0] == rptr[3:0]) ;
endmodule

FIFO/syncFIFO/tbsync_FIFO.v
module tbsync_fifo;
	parameter d_width=16,depth=8;
	reg w,r,clk,rst;
	wire empty,full;
        reg [d_width-1:0] din;
	wire[d_width-1:0] dout;
	wire[$clog2(depth)-1:0] wptr,rptr;
sync_fifo #(.d_width(d_width),.depth(depth)) uut(.w(w),.r(r),.clk(clk),.rst(rst),.empty(empty),.full(full),.din(din),.dout(dout),.wptr(wptr),.rptr(rptr));

always #5 clk = ~clk;
initial begin
	clk=0;rst=1;w=0;r=0;din=$random;
	#10; 
//	rst=0;#10;
//	w=1;#10;din= $random;#10;
//	r=1;#10;
//	w=0;din=$random;#10;
//	w=1;#10;r=0;#40;din=$random;
//	#10;r=1;
//	case 1
	rst=0;
	w=1;r=0;repeat(10) #10 din=$random;w=0;#10;r=1;

	#200 $finish;
end
initial begin 
	$dumpfile("out_fifo.vcd");
	$dumpvars(0,tbsync_fifo);
	$monitor("time=%0t |rst=%b|w=%b|wptr=%d|r=%b|rptr=%d|full=%b|empty=%b|din=%d|dout=%d",$time,rst,w,wptr,r,rptr,full,empty,din,dout);
end
endmodule

FIFO/out_fifo.vcd
$date
	Fri Mar  6 10:56:03 2026
$end
$version
	Icarus Verilog
$end
$timescale
	1s
$end
$scope module tbsync_fifo $end
$var wire 3 ! wptr [2:0] $end
$var wire 3 " rptr [2:0] $end
$var wire 1 # full $end
$var wire 1 $ empty $end
$var wire 16 % dout [15:0] $end
$var parameter 32 & d_width $end
$var parameter 32 ' depth $end
$var reg 1 ( clk $end
$var reg 16 ) din [15:0] $end
$var reg 1 * r $end
$var reg 1 + rst $end
$var reg 1 , w $end
$scope module uut $end
$var wire 1 ( clk $end
$var wire 16 - din [15:0] $end
$var wire 1 * r $end
$var wire 1 + rst $end
$var wire 1 , w $end
$var wire 1 # full $end
$var wire 1 $ empty $end
$var parameter 32 . d_width $end
$var parameter 32 / depth $end
$var reg 16 0 dout [15:0] $end
$var reg 3 1 rptr [2:0] $end
$var reg 3 2 wptr [2:0] $end
$var integer 32 3 i [31:0] $end
$upscope $end
$upscope $end
$enddefinitions $end
$comment Show the parameter values. $end
$dumpall
b1000 /
b10000 .
b1000 '
b10000 &
$end
#0
$dumpvars
bx 3
bx 2
bx 1
bx 0
b11010100100100 -
0,
1+
0*
b11010100100100 )
0(
bx %
x$
x#
bx "
bx !
$end
#5
0#
b0 !
b0 2
b0 "
b0 1
b0 %
b0 0
b1000 3
1(
#10
0(
1,
0+
#15
0$
b1 !
b1 2
1(
#20
0(
b101111010000001 )
b101111010000001 -
#25
b10 !
b10 2
1(
#30
0(
b1101011000001001 )
b1101011000001001 -
#35
b11 !
b11 2
1(
#40
0(
b101011001100011 )
b101011001100011 -
#45
b100 !
b100 2
1(
#50
0(
b111101100001101 )
b111101100001101 -
#55
b101 !
b101 2
1(
#60
0(
b1001100110001101 )
b1001100110001101 -
#65
b110 !
b110 2
1(
#70
0(
b1000010001100101 )
b1000010001100101 -
#75
1#
b111 !
b111 2
1(
#80
0(
b101001000010010 )
b101001000010010 -
#85
1(
#90
0(
b1110001100000001 )
b1110001100000001 -
#95
1(
#100
0(
b1100110100001101 )
b1100110100001101 -
#105
1(
#110
0(
0,
b1111000101110110 )
b1111000101110110 -
#115
1(
#120
0(
1*
#125
0#
b1 "
b1 1
bx %
bx 0
1(
#130
0(
#135
b10 "
b10 1
1(
#140
0(
#145
b11 "
b11 1
1(
#150
0(
#155
b100 "
b100 1
1(
#160
0(
#165
b101 "
b101 1
1(
#170
0(
#175
b110 "
b110 1
1(
#180
0(
#185
x$
b111 "
b111 1
1(
