sequential/counter/async_count.v
module d_ff(
	input d,clk,rst,
	output reg q);
always@(negedge clk )
begin
if (rst)
	q<=0;
else 
	q<=d;
end
endmodule

module asyncount(
	input clk,rst,
	output [3:0]count);
  wire [3:0]q;
	d_ff ff1 (.d(~q[0]),.clk(clk),.rst(rst),.q(q[0]));
	d_ff ff2 (.d(~q[1]),.clk(q[0]),.rst(rst),.q(q[1]));
	d_ff ff3 (.d(~q[2]),.clk(q[1]),.rst(rst),.q(q[2]));
        d_ff ff4 (.d(~q[3]),.clk(q[2]),.rst(rst),.q(q[3]));
       assign count = q;
endmodule

sequential/flipflop/tb_d.v
module tb_d;
	reg d,clk,rst;
	wire q;
d_ff uut(.d(d),.clk(clk),.rst(rst),.q(q));

	always #5 clk = ~clk;
	initial begin
		clk=1;
		rst=0;
		d=0;#5;
		d=1;#10;
		rst=1;
		d=0;#10;rst=0;
		d=1;
		#80 $finish;
	end
	initial begin
		$dumpfile("out_d.vcd");
		$dumpvars(0,tb_d);
		$monitor("Time=%0t,d=%0b,clk=%0b,rst=%0b,q=%0b",$time,d,clk,rst,q);
	end
	endmodule

sequential/flipflop/out_d.vcd
$date
	Mon Feb 16 07:15:18 2026
$end
$version
	Icarus Verilog
$end
$timescale
	1s
$end
$scope module tb_d $end
$var wire 1 ! q $end
$var reg 1 " clk $end
$var reg 1 # d $end
$var reg 1 $ rst $end
$scope module uut $end
$var wire 1 " clk $end
$var wire 1 # d $end
$var wire 1 $ rst $end
$var reg 1 ! q $end
$upscope $end
$upscope $end
$enddefinitions $end
$comment Show the parameter values. $end
$dumpall
$end
#0
$dumpvars
0$
0#
1"
x!
$end
#5
1#
0"
#10
1"
#15
0"
0#
1$
#20
0!
1"
#25
1!
0"
1#
0$
#30
0!
1"
#35
0"
#40
1!
1"
#45
0"
#50
0!
1"
#55
0"
#60
1!
1"
#65
0"
#70
0!
1"
#75
0"
#80
1!
1"
#85
0"
#90
0!
1"
#95
0"
#100
1!
1"
