sequential/clk_div.v
module clkdiv(
	input clk,rst,
	output reg clk_out,
    output  reg [1:0]count);
always @(posedge clk)
begin
	if (rst)begin
		count <= 0;
		clk_out <= 0;
	end
	else if(count == 2'b10  && ~rst)
			begin
				count <=0;
				clk_out <= ~clk_out;
			end
	else
			begin
				count <= count + 1;
				clk_out <= clk_out;
			end
end
endmodule

sequential/tb_clkdiv.v
module tb_clkdiv;
	reg clk,rst;
	wire clk_out;
	wire [1:0]count;
clkdiv uut(.clk(clk),.rst(rst),.clk_out(clk_out),.count(count));

always #5 clk= ~clk;
initial begin
	clk=1;rst=1;
	#10;rst=0;
	#100 $finish;
end
initial begin
	$dumpfile("out_clkdiv.vcd");
	$dumpvars(0,tb_clkdiv);
	$monitor("time=%0t,clk=%b,rst=%b,count=%b,clk_out=%b",$time,clk,rst,count,clk_out);
end
endmodule

sequential/out_clkdiv.vcd
$date
	Wed Feb 25 05:27:29 2026
$end
$version
	Icarus Verilog
$end
$timescale
	1s
$end
$scope module tb_clkdiv $end
$var wire 2 ! count [1:0] $end
$var wire 1 " clk_out $end
$var reg 1 # clk $end
$var reg 1 $ rst $end
$scope module uut $end
$var wire 1 # clk $end
$var wire 1 $ rst $end
$var reg 1 " clk_out $end
$var reg 2 % count [1:0] $end
$upscope $end
$upscope $end
$enddefinitions $end
$comment Show the parameter values. $end
$dumpall
$end
#0
$dumpvars
b0 %
1$
1#
0"
b0 !
$end
#5
0#
#10
b1 !
b1 %
1#
0$
#15
0#
#20
b10 !
b10 %
1#
#25
0#
#30
1"
b0 !
b0 %
1#
#35
0#
#40
b1 !
b1 %
1#
#45
0#
#50
b10 !
b10 %
1#
#55
0#
#60
0"
b0 !
b0 %
1#
#65
0#
#70
b1 !
b1 %
1#
#75
0#
#80
b10 !
b10 %
1#
#85
0#
#90
1"
b0 !
b0 %
1#
#95
0#
#100
b1 !
b1 %
1#
#105
0#
#110
b10 !
b10 %
1#
