sequential/fsm/seq.v
module seq
#(parameter s_w = 3) // state width
	(input clk,rst,d,
	output reg out);
localparam[s_w-1:0]
	s0 = 3'b000, 
	s1 = 3'b001, 
	s2 = 3'b010, 
	s3 = 3'b011, 
	s4 = 3'b100 ;
reg [s_w:0] state,ns;
always@(posedge clk or negedge rst) // 10011 detector
begin
	if (rst)
		state <= s0;
	else 
		state <= ns;
end
always@(*)
begin
	case(state)
		s0:if(d)
			ns <= s1;
		else 
			ns <= s0;
		s1:if(d)
			ns <= s1;
		else 
			ns <= s2;
		s2:if (d)
			ns <= s1;
		else
			ns <= s3;
		s3:if(d)
			ns <= s4;
		else
			ns <= s0;
		s4:if(d)
			ns <= s1;
		else
		       ns <= s2;
       endcase
end
always@(posedge clk or negedge rst)
begin
	if (ns == s4 && d)
		out <= 1;
	else 
		out <= 0;
end
endmodule

sequential/fsm/tb_seq.v
module tb_seq;
	parameter s_w=3;
	reg clk,rst,d;
	wire out;

seq #(.s_w(s_w))  uut (.clk(clk),.rst(rst),.d(d),.out(out));

always #5 clk = ~clk;
initial begin 
	clk = 1;rst=1;d=0;
	#10;rst=0;#10;
	d=1;#10;d=0;#10;d=0;#10;d=1;#10;d=0;#10;
	d=0;#10;d=0;#10;d=1;#10;d=1;#10;d=1;
	#200 $finish;
end
initial begin
	$dumpfile("out_seq.vcd");
	$dumpvars(0,tb_seq);
	$monitor("time=%0t,clk=%b,rst=%b,d=%b,out=%b",$time,clk,rst,d,out);
end
endmodule

sequential/fsm/out_seq.vcd
$date
	Thu Feb 19 12:34:55 2026
$end
$version
	Icarus Verilog
$end
$timescale
	1s
$end
$scope module tb_seq $end
$var wire 1 ! out $end
$var parameter 32 " s_w $end
$var reg 1 # clk $end
$var reg 1 $ d $end
$var reg 1 % rst $end
$scope module uut $end
$var wire 1 # clk $end
$var wire 1 $ d $end
$var wire 1 % rst $end
$var parameter 3 & s0 $end
$var parameter 3 ' s1 $end
$var parameter 3 ( s2 $end
$var parameter 3 ) s3 $end
$var parameter 3 * s4 $end
$var parameter 32 + s_w $end
$var reg 4 , ns [3:0] $end
$var reg 1 ! out $end
$var reg 4 - state [3:0] $end
$upscope $end
$upscope $end
$enddefinitions $end
$comment Show the parameter values. $end
$dumpall
b11 +
b100 *
b11 )
b10 (
b1 '
b0 &
b11 "
$end
#0
$dumpvars
b0 -
b0 ,
1%
0$
1#
0!
$end
#5
0#
#10
1#
0%
#15
0#
#20
b1 ,
1#
1$
#25
0#
#30
b1 -
b10 ,
1#
0$
#35
0#
#40
b11 ,
b10 -
1#
#45
0#
#50
b11 -
b100 ,
1#
1$
#55
0#
#60
b100 -
0!
b10 ,
1#
0$
#65
0#
#70
b11 ,
b10 -
1#
#75
0#
#80
b0 ,
b11 -
1#
#85
0#
#90
b0 -
b1 ,
1#
1$
#95
0#
#100
b1 -
1#
