sequential/counter/sync_counter.v
module syncounter(
	input clk,rst,direc,
	output reg [3:0]count);
always @(posedge clk )
begin
if (rst)
	count <= 4'b0000;
else if(direc) //up counter
	count <= count + 1;
else // down counter
	count <= count -1;
end
endmodule

sequential/counter/tb_sync_counter.v
module tb_count;
	reg clk,rst,direc;
	wire [3:0]count;
syncounter uut(.clk(clk),.rst(rst),.direc(direc),.count(count));

always #5 clk=~clk;
initial begin
	clk=0;rst=1;direc=0;#10;
	rst=0;#10;direc=1;#100;
	direc=0;#100;
	 $finish;
end
initial begin 
	$dumpfile("out_syncount");
	$dumpvars(0,tb_count);
	$monitor("time=%0t,clk=%b,rst=%b,direc=%b,count=%b",$time,clk,rst,direc,count);
end
endmodule

sequential/counter/out_syncount.vcd
$date
	Thu Feb 19 05:48:46 2026
$end
$version
	Icarus Verilog
$end
$timescale
	1s
$end
$scope module tb_count $end
$var wire 4 ! count [3:0] $end
$var reg 1 " clk $end
$var reg 1 # direc $end
$var reg 1 $ rst $end
$scope module uut $end
$var wire 1 " clk $end
$var wire 1 # direc $end
$var wire 1 $ rst $end
$var reg 4 % count [3:0] $end
$upscope $end
$upscope $end
$enddefinitions $end
$comment Show the parameter values. $end
$dumpall
$end
#0
$dumpvars
bx %
1$
0#
0"
bx !
$end
#5
b0 !
b0 %
1"
#10
0"
0$
#15
b1111 !
b1111 %
1"
#20
0"
1#
#25
b0 !
b0 %
1"
#30
0"
#35
b1 !
b1 %
1"
#40
0"
#45
b10 !
b10 %
1"
#50
0"
#55
b11 !
b11 %
1"
#60
0"
#65
b100 !
b100 %
1"
#70
0"
#75
b101 !
b101 %
1"
#80
0"
#85
b110 !
b110 %
1"
#90
0"
#95
b111 !
b111 %
1"
#100
0"
#105
b1000 !
b1000 %
1"
#110
0"
#115
b1001 !
b1001 %
1"
#120
0"
0#
#125
b1000 !
b1000 %
1"
#130
0"
#135
b111 !
b111 %
1"
#140
0"
#145
b110 !
b110 %
1"
#150
0"
#155
b101 !
b101 %
1"
#160
0"
#165
b100 !
b100 %
1"
#170
0"
#175
b11 !
b11 %
1"
#180
0"
#185
b10 !
b10 %
1"
#190
0"
#195
b1 !
b1 %
1"
#200
0"
#205
b0 !
b0 %
1"
#210
0"
#215
b1111 !
b1111 %
1"
