day2/mealyseq.v
module mealy_seq 
#(parameter STATE_WIDTH = 2)
(
	input clk,
	input rst,
	input d,
	output reg q);

 localparam[STATE_WIDTH-1:0]
	S0 = 2'b00,
	S1 = 2'b01,
	S2 = 2'b10;

reg[STATE_WIDTH-1:0] state,next_state;

always@(posedge clk or negedge rst)begin
	if (!rst)
		state <= S0;
	else
		state <= next_state;
	end

always@(*)begin
		next_state = state;
		q = 0;

		case (state)
			S0:begin
				if (d)
			      next_state = S1;
	      		end
			S1:begin
			       	if(!d)
				next_state = S2;
			end
			S2:begin
				if(d)
				begin
				next_state = S1;
				q = 1;
			end
		  		else 
				next_state = S0;
			end
		endcase
end
endmodule

day2/tb_mealyseq.v
module tb_mealyseq;
	reg clk;
	reg rst;
	reg d;
	wire q;

mealy_seq uut (
 	.clk(clk),
	.rst(rst),
	.d(d),
	.q(q)
);

always #5clk = ~clk;

always@(posedge clk)begin
	d <= $random%2 ;
end
initial begin
	clk = 0;
	rst = 0;
	d = 0;
	
	#10 rst = 1;
	#200 $finish;
end
initial begin
	$dumpfile("out_seqmealy.vcd");
	$dumpvars (0,tb_mealyseq);
	$monitor("T=%0t | d=%b | q=%b ",$time,d,q);
end 
endmodule

day2/out_seqmealy.vcd
$date
	Wed Dec 24 09:55:47 2025
$end
$version
	Icarus Verilog
$end
$timescale
	1s
$end
$scope module tb_mealyseq $end
$var wire 1 ! q $end
$var reg 1 " clk $end
$var reg 1 # d $end
$var reg 1 $ rst $end
$scope module uut $end
$var wire 1 " clk $end
$var wire 1 # d $end
$var wire 1 $ rst $end
$var parameter 2 % S0 $end
$var parameter 2 & S1 $end
$var parameter 2 ' S2 $end
$var parameter 32 ( STATE_WIDTH $end
$var reg 2 ) next_state [1:0] $end
$var reg 1 ! q $end
$var reg 2 * state [1:0] $end
$upscope $end
$upscope $end
$enddefinitions $end
$comment Show the parameter values. $end
$dumpall
b10 (
b10 '
b1 &
b0 %
$end
#0
$dumpvars
b0 *
b0 )
0$
0#
0"
0!
$end
#5
1"
#10
0"
1$
#15
b1 )
1#
1"
#20
0"
#25
b1 *
1"
#30
0"
#35
1"
#40
0"
#45
1"
#50
0"
#55
1"
#60
0"
#65
1"
#70
0"
#75
b10 )
0#
1"
#80
0"
#85
1!
b1 )
b10 *
1#
1"
#90
0"
#95
0!
b1 *
1"
#100
0"
#105
b10 )
0#
1"
#110
0"
#115
1!
b1 )
b10 *
1#
1"
#120
0"
#125
0!
b1 *
1"
#130
0"
#135
b10 )
0#
1"
#140
0"
#145
1!
b1 )
b10 *
1#
1"
#150
0"
#155
b10 )
0!
b1 *
0#
1"
#160
0"
#165
1!
b1 )
b10 *
1#
1"
#170
0"
#175
b10 )
0!
b1 *
0#
1"
#180
0"
#185
1!
b1 )
b10 *
1#
1"
#190
0"
#195
0!
b1 *
1"
#200
0"
#205
b10 )
0#
1"
