sequential/sequence.v
module sequence_detector(
	input clk,
	input rst,
	input d,
	output reg Q
);
	reg [2:0] state,next_state;

always @(posedge clk or  negedge rst)begin
	if (!rst)
                state <= 3'b000;	
	else   
		state <= next_state;
       	end
always @(*)begin
	case (state)
		3'b000:begin
			if (d)
				next_state = 3'b001;
			else 
				next_state = 3'b000;
		end
		3'b001:begin
                        if (d)
                                next_state = 3'b001;
                        else
                                next_state = 3'b010;
                end
	        3'b010:begin
                        if (d)
                                next_state = 3'b011;
                        else
                                next_state = 3'b000;
                end
		  3'b011:begin
                        if (d)
                                next_state = 3'b001;
                        else
                                next_state = 3'b000;
                end
	endcase
end

	always @(*) begin
		if (state == 3'b011)
			Q = 1'b1;
		else
			Q = 1'b0;
	end
endmodule

day2/tb_sequence.v
module tb_sequence;
	 reg clk;
	 reg rst;
	 reg d;
	 wire Q;
sequence_detector uut(
	.clk(clk),
	.rst(rst),
	.d(d),
	.Q(Q));
 always # 5 clk = ~clk;

 initial begin
	 clk = 0;
	 rst = 0;
	 d = 0;
        #10  rst = 1;

	@(posedge clk) d <= 1;
	@(posedge clk) d <= 0;
	@(posedge clk) d <= 1;
	@(posedge clk) d <= 1;
	@(posedge clk) d <= 0;
	@(posedge clk) d <= 1;
	@(posedge clk) d <= 0;
	@(posedge clk) d <= 0;
	@(posedge clk) d <= 1;
	@(posedge clk) d <= 0;
	@(posedge clk) d <= 1;
	@(posedge clk) d <= 0;
       #200 $finish;
end
initial begin
	$dumpfile("out_sequence.vcd");
	$dumpvars(0,tb_sequence);
	$monitor("Time=%0t | d=%b | Q=%b", $time, d, Q);
end
endmodule

day2/out_sequence.vcd
$date
	Wed Dec 24 06:47:44 2025
$end
$version
	Icarus Verilog
$end
$timescale
	1s
$end
$scope module tb_sequence $end
$var wire 1 ! Q $end
$var reg 1 " clk $end
$var reg 1 # d $end
$var reg 1 $ rst $end
$scope module uut $end
$var wire 1 " clk $end
$var wire 1 # d $end
$var wire 1 $ rst $end
$var reg 1 ! Q $end
$var reg 3 % next_state [2:0] $end
$var reg 3 & state [2:0] $end
$upscope $end
$upscope $end
$enddefinitions $end
$comment Show the parameter values. $end
$dumpall
$end
#0
$dumpvars
b0 &
b0 %
0$
0#
0"
0!
$end
#5
1"
#10
0"
1$
#15
b1 %
1#
1"
#20
0"
#25
b10 %
b1 &
0#
1"
#30
0"
#35
b11 %
b10 &
1#
1"
#40
0"
#45
1!
b1 %
b11 &
1"
#50
0"
#55
0!
b10 %
b1 &
0#
1"
#60
0"
#65
b11 %
b10 &
1#
1"
#70
0"
#75
1!
b0 %
b11 &
0#
1"
#80
0"
#85
0!
b0 &
1"
#90
0"
#95
b1 %
1#
1"
#100
0"
#105
b10 %
b1 &
0#
1"
#110
0"
#115
b11 %
b10 &
1#
1"
#120
0"
#125
1!
b0 %
b11 &
0#
1"
#130
0"
#135
0!
b0 &
1"
