alu/alu_4bit.v
module alu_4bit(
    input  [3:0] A, B,     // 4-bit inputs
    input  [2:0] ALU_Sel,  // 3-bit control signal
    output reg [3:0] ALU_Out,
    output reg Carry_Out
);

    reg [4:0] tmp;  // 5-bit to hold carry for add/sub

    always @(*) begin
        case (ALU_Sel)
            3'b000: begin // Addition
                tmp = A + B;
                ALU_Out = tmp[3:0];
                Carry_Out = tmp[4];
            end

            3'b001: begin // Subtraction
                tmp = A - B;
                ALU_Out = tmp[3:0];
                Carry_Out = tmp[4];
            end

            3'b010: begin // AND
                ALU_Out = A & B;
                Carry_Out = 0;
            end

            3'b011: begin // OR
                ALU_Out = A | B;
                Carry_Out = 0;
            end

            3'b100: begin // XOR
                ALU_Out = A ^ B;
                Carry_Out = 0;
            end

            3'b101: begin // NOT A
                ALU_Out = ~A;
                Carry_Out = 0;
            end

            3'b110: begin // Shift Left
                ALU_Out = A << 1;
                Carry_Out = 0;
            end

            3'b111: begin // Shift Right
                ALU_Out = A >> 1;
                Carry_Out = 0;
            end

            default: begin
                ALU_Out = 4'b0000;
                Carry_Out = 0;
            end
        endcase
    end

endmodule

alu/tb_alu_4bit.v
module tb_alu_4bit;

    // Inputs
    reg [3:0] A;
    reg [3:0] B;
    reg [2:0] ALU_Sel;

    // Outputs
    wire [3:0] ALU_Out;
    wire Carry_Out;

    // Instantiate the ALU
    alu_4bit uut (
        .A(A),
        .B(B),
        .ALU_Sel(ALU_Sel),
        .ALU_Out(ALU_Out),
        .Carry_Out(Carry_Out)
    );

    initial begin
    $dumpfile("alu_4bit.vcd");
    $dumpvars(0,tb_alu_4bit);
    A=4'b0011;B=4'b0001;ALU_Sel=3'b000;#200;
    A=4'b0011;B=4'b0001;ALU_Sel=3'b001;#200;
    A=4'b0011;B=4'b0001;ALU_Sel=3'b010;#200;
    A=4'b0011;B=4'b0001;ALU_Sel=3'b011;#200;
    A=4'b0011;B=4'b0001;ALU_Sel=3'b100;#200;
    A=4'b0011;B=4'b0001;ALU_Sel=3'b101;#200;
    A=4'b0011;B=4'b0001;ALU_Sel=3'b110;#200;
    A=4'b0011;B=4'b0001;ALU_Sel=3'b111;#200;
    $finish;
    end
   
    initial begin
        $monitor("Time = %0d | A = %b | B = %b | ALU_Sel = %b | ALU_Out = %b | Carry_Out = %b",
                 $time, A, B, ALU_Sel, ALU_Out, Carry_Out);
    end

    
 
endmodule

alu/alu_4bit.vcd
$date
	Sat Sep 13 15:53:02 2025
$end
$version
	Icarus Verilog
$end
$timescale
	1s
$end
$scope module tb_alu_4bit $end
$var wire 1 ! Carry_Out $end
$var wire 4 " ALU_Out [3:0] $end
$var reg 4 # A [3:0] $end
$var reg 3 $ ALU_Sel [2:0] $end
$var reg 4 % B [3:0] $end
$scope module uut $end
$var wire 4 & A [3:0] $end
$var wire 3 ' ALU_Sel [2:0] $end
$var wire 4 ( B [3:0] $end
$var reg 4 ) ALU_Out [3:0] $end
$var reg 1 ! Carry_Out $end
$var reg 5 * tmp [4:0] $end
$upscope $end
$upscope $end
$enddefinitions $end
$comment Show the parameter values. $end
$dumpall
$end
#0
$dumpvars
b100 *
b100 )
b1 (
b0 '
b11 &
b1 %
b0 $
b11 #
b100 "
0!
$end
#200
b10 "
b10 )
b10 *
b1 $
b1 '
#400
b1 "
b1 )
b10 $
b10 '
#600
b11 "
b11 )
b11 $
b11 '
#800
b10 "
b10 )
b100 $
b100 '
#1000
b1100 "
b1100 )
b101 $
b101 '
#1200
b110 "
b110 )
b110 $
b110 '
#1400
b1 "
b1 )
b111 $
b111 '
