combinational/demux.v
module demux(
    input y,
    input [1:0] sel,
    output reg a,b,c,d);
    always @(*)
    begin 
            a=0;b=0;c=0;d=0;
        if (~sel[1] && ~sel[0])
            a = y;
            else if (~sel[1] && sel[0])
                b=y;
                else if (sel[1] && ~sel[0])
                c=y;
                else 
                d=y;
    end
endmodule

combinational/tb_demux.v
module tb_demux;
    reg y;
    reg [1:0]sel;
    wire a,b,c,d;
    integer i;
 demux  uut(.y(y),.sel(sel),.a(a),.b(b),.c(c),.d(d));
 initial begin
    sel[0]=0;sel[1]=0;y=0; #10;
    for  (i=0;i<16;i++) begin
    {sel[1],sel[0],y}=i;#10;
 end
 end

 initial begin
       $dumpfile("out_demux");
       $dumpvars(0,tb_demux);	
       $monitor("time=%0t,sel[1]=%0b,sel[0]=%0b,y=%0b,a=%0b,b=%0b,c=%0b,d=%0b",$time,sel[1],sel[0],y,a,b,c,d);
      #100; $finish;
       end
 endmodule

combinational/out_demux.vcd
$date
	Thu Feb 12 07:05:42 2026
$end
$version
	Icarus Verilog
$end
$timescale
	1s
$end
$scope module tb_demux $end
$var wire 1 ! d $end
$var wire 1 " c $end
$var wire 1 # b $end
$var wire 1 $ a $end
$var reg 2 % sel [1:0] $end
$var reg 1 & y $end
$var integer 32 ' i [31:0] $end
$scope module uut $end
$var wire 2 ( sel [1:0] $end
$var wire 1 & y $end
$var reg 1 $ a $end
$var reg 1 # b $end
$var reg 1 " c $end
$var reg 1 ! d $end
$upscope $end
$upscope $end
$enddefinitions $end
$comment Show the parameter values. $end
$dumpall
$end
#0
$dumpvars
b0 (
bx '
0&
b0 %
0$
0#
0"
0!
$end
#10
b0 '
#20
1$
1&
b1 '
#30
0$
b1 %
b1 (
0&
b10 '
#40
1#
1&
b11 '
#50
0#
b10 %
b10 (
0&
b100 '
#60
1"
1&
b101 '
#70
0"
b11 %
b11 (
0&
b110 '
#80
1!
1&
b111 '
#90
0!
b0 %
b0 (
0&
b1000 '
#100
1$
1&
b1001 '
