FIFO/asyncFIFO/fifo_mem.v
module fifo_mem #(parameter d_width=8,depth=8,ptr_width=4)
(input wclk,rclk,we,re,full,empty,
input [ptr_width-1:0]b_wptr,b_rptr,
input [d_width-1:0]w_data,
output reg [d_width-1:0]r_dout);
reg [d_width-1:0]fifo_mem[depth-1:0];
always @(posedge wclk)
begin
	if( we && !full)
	begin
		fifo_mem[b_wptr] <= w_data;
	end
end
always @(posedge rclk)
begin
	if(re && !empty)
	begin
		r_dout <= fifo_mem[b_rptr];
	end
end
endmodule

FIFO/asyncFIFO/rptr_handler.v
module rptr_handler # (parameter ptr_width = 4,depth = 8)
        (input rclk,rrst,re,
         input [ptr_width-1:0] sync_gwptr,
         output reg [ptr_width-1:0] b_rptr,
	 output [ptr_width-1:0]g_rptr,
         output empty);
wire [ptr_width-1:0] nxtb_rptr,nxtg_rptr;
assign nxtb_rptr = b_rptr + (re & !empty);
assign nxtg_rptr = (nxtb_rptr >> 1)^nxtb_rptr;
always @(posedge rclk or negedge rrst)
begin
if(!rrst)
        b_rptr <= 0;
else if (re && !empty)
        b_rptr <= nxtb_rptr;
end
assign g_rptr = (b_rptr >> 1)^b_rptr;
assign empty = (sync_gwptr == g_rptr);
endmodule

FIFO/asyncFIFO/wptr_handler.v
module wptr_handler # (parameter ptr_width = 4,depth = 8)
	(input wclk,wrst,we,
	 input [ptr_width-1:0] sync_grptr,
	 output reg [ptr_width-1:0] b_wptr,
	 output [ptr_width-1:0] g_wptr,
	 output full);
 wire [ptr_width-1:0] nxtb_wptr,nxtg_wptr;
 assign  nxtb_wptr = b_wptr + (we & !full);
assign  nxtg_wptr = (nxtb_wptr >> 1)^nxtb_wptr;
always @(posedge wclk or negedge wrst)
begin
if(!wrst)
	b_wptr <= 0;
else if ( we && !full) 
	b_wptr <= nxtb_wptr;
end
assign g_wptr = (b_wptr >> 1)^b_wptr;
assign full = (g_wptr == {~sync_grptr[ptr_width-1:ptr_width-2],sync_grptr[ptr_width-3:0]});
endmodule

FIFO/asyncFIFO/read_wsync.v
module r_wsync # (parameter ptr_width = 4)
	(input [ptr_width-1:0] g_rptr,
	input wclk,wrst,
	output reg [ptr_width-1:0] sync_grptr);
reg [ptr_width-1:0] din;  
always@(posedge wclk or negedge wrst)
begin
if (!wrst)
 begin
	sync_grptr <= 0;
	din <= 0;
end
else
begin 
	din <= g_rptr;
	sync_grptr <= din; 
end
end
endmodule

FIFO/asyncFIFO/write_rsync.v
module w_rsync  #(parameter ptr_width = 4)
        (input [ptr_width-1:0] g_wptr,
        input rclk,rrst,
        output reg [ptr_width-1:0] sync_gwptr);
reg [ptr_width-1:0] din;
always@(posedge rclk or negedge rrst)
begin
if (!rrst)
 begin
        sync_gwptr <= 0;
        din <= 0;
end
else
begin
        din <= g_wptr;
        sync_gwptr <= din;
end
end
endmodule

FIFO/asyncFIFO/fifo_top.v
`include "read_wsync.v" 
`include "rptr_handler.v"
`include "wptr_handler.v"
`include "write_rsync.v"
`include "fifo_mem.v"

module top #(parameter d_width = 8 , ptr_width = 4 )
	(input wclk,rclk,wrst,rrst,we,re,
	input [d_width-1:0] w_data,
	output [d_width-1:0] r_dout,
	output full ,empty);
wire [ptr_width-1:0] g_wptr,g_rptr,b_wptr,b_rptr;
wire [ptr_width-1:0] sync_gwptr,sync_grptr;

w_rsync b1 (.rclk(rclk),
	.rrst(rrst),
	.g_wptr(g_wptr),
	.sync_gwptr(sync_gwptr));

r_wsync b2 (.wclk(wclk),
	.wrst(wrst),
	.g_rptr(g_rptr),
	.sync_grptr(sync_grptr));

wptr_handler b3 (.wclk(wclk),
	.wrst(wrst),
	.we(we),
	.sync_grptr(sync_grptr),
	.b_wptr(b_wptr),
	.g_wptr(g_wptr),
	.full(full));

rptr_handler b4 (.rclk(rclk),
	.rrst(rrst),
	.re(re),
	.sync_gwptr(sync_gwptr),
	.b_rptr(b_rptr),
	.g_rptr(g_rptr),
	.empty(empty));

fifo_mem b5 (.wclk(wclk),
	.rclk(rclk),
	.we(we),
	.re(re),
	.full(full),
	.empty(empty),
	.b_wptr(b_wptr),
	.b_rptr(b_rptr),
	.w_data(w_data),
	.r_dout(r_dout));

endmodule

FIFO/asyncFIFO/tb_async_fifo.v
module tb_asyncfifo;
	parameter d_width=8,ptr_width=4;
	reg wclk,rclk,wrst,rrst,we,re;
	reg [d_width-1:0]w_data;
        wire[d_width-1:0] r_dout;
	wire full ,empty;
top #(.d_width(d_width),.ptr_width(ptr_width)) uut (.*);
always #5 wclk = ~wclk;
always #10 rclk = ~rclk;
initial begin
	 wclk=0;rclk=0;wrst=0;rrst=0;we=0;re=0;w_data=8'd1;
	 #10;
	 wrst=1;rrst=1;we=1;
	 #10; 
	 w_data=8'd10;
	 #10;
	 w_data=8'd16;
	 #10;re=1;we=0;
	 #40;
	 we=1;#10;w_data=8'd12;
	 #10;w_data=8'd6;
	 /*repeat (8) 
 	 begin 
		#10;
		w_data=$random;
         end
	 #10;
	 repeat(8)
	 begin 
	 #10;
	 we=0;
         re=1;
  	 end

	 #10; we=1;re=1;
	 #10; repeat(5) #10 w_data=$random;*/
	 #100 $finish;
 end
 initial begin
	 $dumpfile("out_asyncfifo.vcd");
	 $dumpvars(0,tb_asyncfifo);
	 $monitor ("time=%0t |wclk=%b|rclk=%b|wrst=%b|rrst=%b|we=%b|re=%b|w_data=%d|b_wptr=%d|b_rptr=%d|full=%b|empty=%b|r_dout=%d",$time,wclk,rclk,wrst,rrst,we,re,w_data,uut.b_wptr,uut.b_rptr,full,empty,r_dout);
 end
 endmodule

FIFO/asyncFIFO/out_asyncfifo.vcd
$date
	Tue Mar 10 11:17:51 2026
$end
$version
	Icarus Verilog
$end
$timescale
	1s
$end
$scope module tb_asyncfifo $end
$var wire 8 ! r_dout [7:0] $end
$var wire 1 " full $end
$var wire 1 # empty $end
$var parameter 32 $ d_width $end
$var parameter 32 % ptr_width $end
$var reg 1 & rclk $end
$var reg 1 ' re $end
$var reg 1 ( rrst $end
$var reg 8 ) w_data [7:0] $end
$var reg 1 * wclk $end
$var reg 1 + we $end
$var reg 1 , wrst $end
$scope module uut $end
$var wire 1 & rclk $end
$var wire 1 ' re $end
$var wire 1 ( rrst $end
$var wire 8 - w_data [7:0] $end
$var wire 1 * wclk $end
$var wire 1 + we $end
$var wire 1 , wrst $end
$var wire 4 . sync_gwptr [3:0] $end
$var wire 4 / sync_grptr [3:0] $end
$var wire 8 0 r_dout [7:0] $end
$var wire 4 1 g_wptr [3:0] $end
$var wire 4 2 g_rptr [3:0] $end
$var wire 1 " full $end
$var wire 1 # empty $end
$var wire 4 3 b_wptr [3:0] $end
$var wire 4 4 b_rptr [3:0] $end
$var parameter 32 5 d_width $end
$var parameter 32 6 ptr_width $end
$scope module b1 $end
$var wire 1 & rclk $end
$var wire 1 ( rrst $end
$var wire 4 7 g_wptr [3:0] $end
$var parameter 32 8 ptr_width $end
$var reg 4 9 din [3:0] $end
$var reg 4 : sync_gwptr [3:0] $end
$upscope $end
$scope module b2 $end
$var wire 1 * wclk $end
$var wire 1 , wrst $end
$var wire 4 ; g_rptr [3:0] $end
$var parameter 32 < ptr_width $end
$var reg 4 = din [3:0] $end
$var reg 4 > sync_grptr [3:0] $end
$upscope $end
$scope module b3 $end
$var wire 4 ? g_wptr [3:0] $end
$var wire 4 @ nxtg_wptr [3:0] $end
$var wire 4 A sync_grptr [3:0] $end
$var wire 1 * wclk $end
$var wire 1 + we $end
$var wire 1 , wrst $end
$var wire 4 B nxtb_wptr [3:0] $end
$var wire 1 " full $end
$var parameter 32 C depth $end
$var parameter 32 D ptr_width $end
$var reg 4 E b_wptr [3:0] $end
$upscope $end
$scope module b4 $end
$var wire 4 F g_rptr [3:0] $end
$var wire 4 G nxtg_rptr [3:0] $end
$var wire 1 & rclk $end
$var wire 1 ' re $end
$var wire 1 ( rrst $end
$var wire 4 H sync_gwptr [3:0] $end
$var wire 4 I nxtb_rptr [3:0] $end
$var wire 1 # empty $end
$var parameter 32 J depth $end
$var parameter 32 K ptr_width $end
$var reg 4 L b_rptr [3:0] $end
$upscope $end
$scope module b5 $end
$var wire 4 M b_rptr [3:0] $end
$var wire 4 N b_wptr [3:0] $end
$var wire 1 # empty $end
$var wire 1 " full $end
$var wire 1 & rclk $end
$var wire 1 ' re $end
$var wire 8 O w_data [7:0] $end
$var wire 1 * wclk $end
$var wire 1 + we $end
$var parameter 32 P d_width $end
$var parameter 32 Q depth $end
$var parameter 32 R ptr_width $end
$var reg 8 S r_dout [7:0] $end
$upscope $end
$upscope $end
$upscope $end
$enddefinitions $end
$comment Show the parameter values. $end
$dumpall
b100 R
b1000 Q
b1000 P
b100 K
b1000 J
b100 D
b1000 C
b100 <
b100 8
b100 6
b1000 5
b100 %
b1000 $
$end
#0
$dumpvars
bx S
b1 O
b0 N
b0 M
b0 L
b0 I
b0 H
b0 G
b0 F
b0 E
b0 B
b0 A
b0 @
b0 ?
b0 >
b0 =
b0 ;
b0 :
b0 9
b0 7
b0 4
b0 3
b0 2
b0 1
bx 0
b0 /
b0 .
b1 -
0,
0+
0*
b1 )
0(
0'
0&
1#
0"
bx !
$end
#5
1*
#10
b1 @
b1 B
0*
1+
1(
1,
1&
#15
b11 @
b1 1
b1 7
b1 ?
b10 B
b1 3
b1 E
b1 N
1*
#20
0*
b1010 )
b1010 -
b1010 O
0&
#25
b10 @
b11 1
b11 7
b11 ?
b11 B
b10 3
b10 E
b10 N
1*
#30
b11 9
0*
b10000 )
b10000 -
b10000 O
1&
#35
b110 @
b10 1
b10 7
b10 ?
b100 B
b11 3
b11 E
b11 N
1*
#40
b10 @
b11 B
0*
0+
1'
0&
#45
1*
#50
b1 G
b1 I
0#
b11 .
b11 :
b11 H
b10 9
0*
1&
#55
1*
#60
0*
0&
#65
1*
#70
b11 G
b1 2
b1 ;
b1 F
b10 .
b10 :
b10 H
b10 I
b1 4
b1 L
b1 M
b1 !
b1 0
b1 S
0*
1&
#75
b1 =
1*
#80
b110 @
b100 B
0*
0&
1+
#85
b111 @
b110 1
b110 7
b110 ?
b101 B
b100 3
b100 E
b100 N
b1 /
b1 >
b1 A
1*
#90
b10 G
0#
b11 2
b11 ;
b11 F
b11 I
b10 4
b10 L
b10 M
b110 9
b1010 !
b1010 0
b1010 S
0*
1&
b1100 )
b1100 -
b1100 O
#95
b101 @
b111 1
b111 7
b111 ?
b11 =
b110 B
b101 3
b101 E
b101 N
1*
#100
0*
0&
b110 )
b110 -
b110 O
#105
b100 @
b101 1
b101 7
b101 ?
b111 B
b110 3
b110 E
b110 N
b11 /
b11 >
b11 A
1*
#110
b110 G
b10 2
b10 ;
b10 F
b110 .
b110 :
b110 H
b101 9
b100 I
b11 4
b11 L
b11 M
b10000 !
b10000 0
b10000 S
0*
1&
#115
b1100 @
b100 1
b100 7
b100 ?
b10 =
b1000 B
b111 3
b111 E
b111 N
1*
#120
0*
0&
#125
b1101 @
b1100 1
b1100 7
b1100 ?
b1001 B
b1000 3
b1000 E
b1000 N
b10 /
b10 >
b10 A
1*
#130
b111 G
0#
b110 2
b110 ;
b110 F
b101 I
b100 4
b100 L
b100 M
b101 .
b101 :
b101 H
b1100 9
0*
1&
#135
b1111 @
b1101 1
b1101 7
b1101 ?
b110 =
b1010 B
b1001 3
b1001 E
b1001 N
1*
#140
0*
0&
#145
b1110 @
0"
b1111 1
b1111 7
b1111 ?
b1011 B
b1010 3
b1010 E
b1010 N
b110 /
b110 >
b110 A
1*
#150
b101 G
b111 2
b111 ;
b111 F
b1100 .
b1100 :
b1100 H
b1111 9
b110 I
b101 4
b101 L
b101 M
b1100 !
b1100 0
b1100 S
0*
1&
#155
b1010 @
b1110 1
b1110 7
b1110 ?
b111 =
b1100 B
b1011 3
b1011 E
b1011 N
1*
#160
0*
0&
#165
b1011 @
b1010 1
b1010 7
b1010 ?
b1101 B
b1100 3
b1100 E
b1100 N
b111 /
b111 >
b111 A
1*
#170
b100 G
b101 2
b101 ;
b101 F
b111 I
b110 4
b110 L
b110 M
b1111 .
b1111 :
b1111 H
b1010 9
b110 !
b110 0
b110 S
0*
1&
#175
b1011 @
1"
b1011 1
b1011 7
b1011 ?
b101 =
b1101 B
b1101 3
b1101 E
b1101 N
1*
#180
0*
0&
#185
b1001 @
b1110 B
0"
b101 /
b101 >
b101 A
1*
#190
b1100 G
b100 2
b100 ;
b100 F
b1010 .
b1010 :
b1010 H
b1011 9
b1000 I
b111 4
b111 L
b111 M
0*
1&
#195
1"
b1001 @
b1001 1
b1001 7
b1001 ?
b100 =
b1110 B
b1110 3
b1110 E
b1110 N
1*
